expert/__init__.py
expert/version.py
expert/CLI/CLI_utils.py
expert/CLI/__init__.py
expert/CLI/main.py
expert/CLI/main_construct.py
expert/CLI/main_convert.py
expert/CLI/main_download.py
expert/CLI/main_evaluate.py
expert/CLI/main_init.py
expert/CLI/main_map.py
expert/CLI/main_search.py
expert/CLI/main_select.py
expert/CLI/main_train.py
expert/CLI/main_transfer.py
expert/resources/config.ini
expert/resources/phylogeny.csv
expert/resources/general_model/ontology.pkl
expert/resources/general_model/statistics.csv
expert/resources/general_model/base/saved_model.pb
expert/resources/general_model/base/variables/variables.data-00000-of-00001
expert/resources/general_model/base/variables/variables.index
expert/resources/general_model/integs/0/saved_model.pb
expert/resources/general_model/integs/0/variables/variables.data-00000-of-00001
expert/resources/general_model/integs/0/variables/variables.index
expert/resources/general_model/integs/1/saved_model.pb
expert/resources/general_model/integs/1/variables/variables.data-00000-of-00001
expert/resources/general_model/integs/1/variables/variables.index
expert/resources/general_model/integs/2/saved_model.pb
expert/resources/general_model/integs/2/variables/variables.data-00000-of-00001
expert/resources/general_model/integs/2/variables/variables.index
expert/resources/general_model/integs/3/saved_model.pb
expert/resources/general_model/integs/3/variables/variables.data-00000-of-00001
expert/resources/general_model/integs/3/variables/variables.index
expert/resources/general_model/integs/4/saved_model.pb
expert/resources/general_model/integs/4/variables/variables.data-00000-of-00001
expert/resources/general_model/integs/4/variables/variables.index
expert/resources/general_model/inters/0/saved_model.pb
expert/resources/general_model/inters/0/variables/variables.data-00000-of-00001
expert/resources/general_model/inters/0/variables/variables.index
expert/resources/general_model/inters/1/saved_model.pb
expert_mst-0.3.dist-info/LICENSE
expert_mst-0.3.dist-info/METADATA
expert_mst-0.3.dist-info/WHEEL
expert_mst-0.3.dist-info/entry_points.txt
expert_mst-0.3.dist-info/top_level.txt
expert_mst-0.3.dist-info/zip-safe
expert_mst-0.3.dist-info/RECORD
