Metadata-Version: 2.1
Name: expert-mst
Version: 0.3
Summary: Exact and pervasive expert model for source tracking based on transfer learning
Home-page: https://github.com/HUST-NingKang-Lab/EXPERT
Author: Hui Chong
Author-email: huichong.me@gmail.com
License: MIT
Platform: UNKNOWN
Classifier: Topic :: Scientific/Engineering :: Bio-Informatics
Classifier: Programming Language :: Python :: 3.8
Classifier: Development Status :: 4 - Beta
Classifier: License :: OSI Approved :: MIT License
Classifier: Operating System :: OS Independent
Classifier: Natural Language :: English
Requires-Python: >=3.6
Requires-Dist: setuptools (>=40.6.3)
Requires-Dist: pandas (>=1.1.1)
Requires-Dist: tables (>=3.6.1)
Requires-Dist: tqdm (>=4.46.0)
Requires-Dist: numpy (>=1.18.5)
Requires-Dist: scikit-learn (>=0.23.1)
Requires-Dist: tensorflow-cpu (>=2.3.0)
Requires-Dist: living-tree (==0.0.5)
Requires-Dist: treelib (==1.5.5)
Requires-Dist: seaborn (>=0.11.0)
